.travis.yml
.zopeskel
CHANGES.txt
CONTRIBUTORS.txt
Makefile
README.txt
setup.py
docs/LICENSE.GPL
docs/LICENSE.txt
docs/Makefile
docs/source/conf.py
docs/source/index.rst
docs/source/_static/.empty
docs/source/_templates/indexsidebar.html
docs/source/_themes/bootstrap.zip
pigeonhole/__init__.py
pigeonhole/rendering.py
pigeonhole.egg-info/PKG-INFO
pigeonhole.egg-info/SOURCES.txt
pigeonhole.egg-info/dependency_links.txt
pigeonhole.egg-info/entry_points.txt
pigeonhole.egg-info/not-zip-safe
pigeonhole.egg-info/requires.txt
pigeonhole.egg-info/top_level.txt
pigeonhole/tests/__init__.py
pigeonhole/tests/test_pigeonhole.py