Metadata-Version: 1.1
Name: pigeonhole
Version: 0.1
Summary: Dashboard development tool
Home-page: https://github.com/maikroeder/pigeonhole.git
Author: Maik Roeder
Author-email: roeder@berg.net
License: gpl
Platform: UNKNOWN
Classifier: Programming Language :: Python
